README.md
setup.py
vape_models/__init__.py
vape_models/base_pod.py
vape_models/comments.py
vape_models/companies.py
vape_models/liquids.py
vape_models/vaporizers.py
vape_models.egg-info/PKG-INFO
vape_models.egg-info/SOURCES.txt
vape_models.egg-info/dependency_links.txt
vape_models.egg-info/requires.txt
vape_models.egg-info/top_level.txt